cm/__init__.py
cm/cm.py
Cloudimate-0.1.dist-info/METADATA
Cloudimate-0.1.dist-info/WHEEL
Cloudimate-0.1.dist-info/entry_points.txt
Cloudimate-0.1.dist-info/top_level.txt
Cloudimate-0.1.dist-info/RECORD
